Metadata-Version: 2.1
Name: Salesforce-FuelSDK
Version: 1.2.0
Summary: Salesforce Marketing Cloud Fuel SDK for Python
Home-page: https://github.com/salesforce-marketingcloud/FuelSDK-Python
Author: ExactTarget
License: MIT
Platform: UNKNOWN
Classifier: Development Status :: 4 - Beta
Classifier: Intended Audience :: Developers
Classifier: License :: OSI Approved :: MIT License
Classifier: Operating System :: OS Independent
Classifier: Topic :: Software Development :: Libraries
Classifier: Programming Language :: Python :: 3.3
Requires-Dist: pyjwt (>=1.5.3)
Requires-Dist: requests (>=2.18.4)
Requires-Dist: suds-jurko (==0.6)
